dataschema/Schema.py
dataschema/Schema_pb2.py
dataschema/__init__.py
dataschema/annotations.py
dataschema/data_writer.py
dataschema/entity.py
dataschema/parquet2schema.py
dataschema/proto2schema.py
dataschema/pyspark2schema.py
dataschema/python2schema.py
dataschema/schema2beam.py
dataschema/schema2dbml.py
dataschema/schema2expectations.py
dataschema/schema2pandas.py
dataschema/schema2parquet.py
dataschema/schema2pyspark.py
dataschema/schema2python.py
dataschema/schema2scala.py
dataschema/schema2sql.py
dataschema/schema2sqlalchemy.py
dataschema/schema_synth.py
dataschema/schema_synth_generator.py
dataschema/schema_types.py
dataschema/strutil.py
dataschema/synthgen.py
sql_analyze/__init__.py
sql_analyze/grammars/__init__.py
sql_analyze/grammars/graphing.py
sql_analyze/grammars/parse_sql.py
sql_analyze/grammars/parse_sql_flags.py
sql_analyze/grammars/parse_sql_lib.py
sql_analyze/grammars/statement.py
sql_analyze/grammars/tokens.py
sql_analyze/grammars/trees.py
sql_analyze/grammars/ClickHouse/ClickHouseLexer.py
sql_analyze/grammars/ClickHouse/ClickHouseParser.py
sql_analyze/grammars/ClickHouse/ClickHouseParserVisitor.py
sql_analyze/grammars/ClickHouse/__init__.py
sql_analyze/grammars/ClickHouse/create_table_schema.py
sql_analyze/grammars/ClickHouse/parse_sql_lib.py
sql_analyze/grammars/ClickHouse/statement_builder.py
sql_analyze/grammars/Hive/HiveLexer.py
sql_analyze/grammars/Hive/HiveParser.py
sql_analyze/grammars/Hive/HiveParserVisitor.py
sql_analyze/grammars/Hive/__init__.py
sql_analyze/grammars/Hive/parse_sql_lib.py
sql_analyze/grammars/Hive/statement_builder.py
sql_analyze/viewer/__init__.py
sql_analyze/viewer/viewer.py
sql_analyze/viewer/examples/exists_aggregate.sql
sql_analyze/viewer/examples/exists_having.sql
sql_analyze/viewer/examples/exists_join_set.sql
sql_analyze/viewer/examples/exists_within.sql
sql_analyze/viewer/examples/join_outer.sql
sql_analyze/viewer/examples/subquery_correlated.sql
sql_analyze/viewer/examples/subquery_correlated_scalar.sql
nuna_sql_tools-0.0.34.dist-info/LICENSE
nuna_sql_tools-0.0.34.dist-info/METADATA
nuna_sql_tools-0.0.34.dist-info/WHEEL
nuna_sql_tools-0.0.34.dist-info/entry_points.txt
nuna_sql_tools-0.0.34.dist-info/top_level.txt
nuna_sql_tools-0.0.34.dist-info/RECORD
