Metadata-Version: 2.1
Name: nuna-sql-tools
Version: 0.0.34
Summary: Nuna Sql Tools contains utilities to create and manipulate schemas and sql statements.
Home-page: https://github.com/NunaInc/sql_tools
Download-URL: https://github.com/NunaInc/sql_tools
Author: Nuna Inc.
Author-email: catalin@nuna.com
License: Apache 2.0
Platform: UNKNOWN
Classifier: Development Status :: 3 - Alpha
Classifier: Topic :: Database
Classifier: Topic :: Software Development :: Libraries
Classifier: Programming Language :: SQL
Classifier: Programming Language :: Python :: 3 :: Only
Classifier: License :: OSI Approved :: Apache Software License
Classifier: Intended Audience :: Developers
License-File: LICENSE
Requires-Dist: absl-py (==0.13.0)
Requires-Dist: protobuf (<4,>=3.19.0)
Provides-Extra: faker
Requires-Dist: Faker (==8.13.2) ; extra == 'faker'
Provides-Extra: sqlalchemy_1.4.16
Requires-Dist: SQLAlchemy (>=1.4.16) ; extra == 'sqlalchemy_1.4.16'
Provides-Extra: antlr4-python3-runtime
Requires-Dist: antlr4-python3-runtime (==4.9.3) ; extra == 'antlr4-python3-runtime'
Provides-Extra: apache-beam
Requires-Dist: apache-beam (==2.43.0) ; extra == 'apache-beam'
Provides-Extra: graphviz
Requires-Dist: graphviz (==0.19.1) ; extra == 'graphviz'
Provides-Extra: great_expectations
Requires-Dist: great-expectations (==0.14.12) ; extra == 'great_expectations'
Provides-Extra: numpy_1.21.2
Requires-Dist: numpy (>=1.21.2) ; extra == 'numpy_1.21.2'
Provides-Extra: pandas_1.3.3_2
Requires-Dist: pandas (<2,>=1.3.3) ; extra == 'pandas_1.3.3_2'
Provides-Extra: pyarrow_7.0.0_11
Requires-Dist: pyarrow (<11,>=7.0.0) ; extra == 'pyarrow_7.0.0_11'
Provides-Extra: pyspark
Requires-Dist: pyspark (==3.2.1) ; extra == 'pyspark'
Provides-Extra: s3fs_2022.3.0
Requires-Dist: s3fs (>=2022.3.0) ; extra == 's3fs_2022.3.0'
Provides-Extra: smart_open
Requires-Dist: smart-open[all] (==6.0.0) ; extra == 'smart_open'
